[
    {
        "status": "completed", 
        "check_run_url": "https://api.github.com/repos/soramitsu/soramitsu-hunter/check-runs/1797249503", 
        "name": "spdlog analyze-cxx17 ubuntu-16.04", 
        "run_id": 523288990, 
        "url": "https://api.github.com/repos/soramitsu/soramitsu-hunter/actions/jobs/1797249503", 
        "html_url": "https://github.com/soramitsu/soramitsu-hunter/runs/1797249503", 
        "completed_at": "2021-01-30T12:08:16Z", 
        "run_url": "https://api.github.com/repos/soramitsu/soramitsu-hunter/actions/runs/523288990", 
        "node_id": "MDg6Q2hlY2tSdW4xNzk3MjQ5NTAz", 
        "steps": [
            {
                "status": "completed", 
                "name": "Set up job", 
                "number": 1, 
                "completed_at": "2021-01-30T12:07:22.000Z", 
                "started_at": "2021-01-30T12:07:20.000Z", 
                "conclusion": "success"
            }, 
            {
                "status": "completed", 
                "name": "Git checkout with submodules", 
                "number": 2, 
                "completed_at": "2021-01-30T12:07:26.000Z", 
                "started_at": "2021-01-30T12:07:22.000Z", 
                "conclusion": "success"
            }, 
            {
                "status": "completed", 
                "name": "Set up Python", 
                "number": 3, 
                "completed_at": "2021-01-30T12:07:26.000Z", 
                "started_at": "2021-01-30T12:07:26.000Z", 
                "conclusion": "success"
            }, 
            {
                "status": "completed", 
                "name": "Set up Python environment variable (Unix)", 
                "number": 4, 
                "completed_at": "2021-01-30T12:07:26.000Z", 
                "started_at": "2021-01-30T12:07:26.000Z", 
                "conclusion": "success"
            }, 
            {
                "status": "completed", 
                "name": "Set up Python environment variable (Windows)", 
                "number": 5, 
                "completed_at": "2021-01-30T12:07:26.000Z", 
                "started_at": "2021-01-30T12:07:26.000Z", 
                "conclusion": "skipped"
            }, 
            {
                "status": "completed", 
                "name": "Extract branch name", 
                "number": 6, 
                "completed_at": "2021-01-30T12:07:26.000Z", 
                "started_at": "2021-01-30T12:07:26.000Z", 
                "conclusion": "success"
            }, 
            {
                "status": "completed", 
                "name": "Upgrade pip", 
                "number": 7, 
                "completed_at": "2021-01-30T12:07:30.000Z", 
                "started_at": "2021-01-30T12:07:26.000Z", 
                "conclusion": "success"
            }, 
            {
                "status": "completed", 
                "name": "Build on Unix", 
                "number": 8, 
                "completed_at": "2021-01-30T12:08:16.000Z", 
                "started_at": "2021-01-30T12:07:30.000Z", 
                "conclusion": "success"
            }, 
            {
                "status": "completed", 
                "name": "Build on Windows", 
                "number": 9, 
                "completed_at": "2021-01-30T12:08:16.000Z", 
                "started_at": "2021-01-30T12:08:16.000Z", 
                "conclusion": "skipped"
            }, 
            {
                "status": "completed", 
                "name": "Post Git checkout with submodules", 
                "number": 18, 
                "completed_at": "2021-01-30T12:08:16.000Z", 
                "started_at": "2021-01-30T12:08:16.000Z", 
                "conclusion": "success"
            }, 
            {
                "status": "completed", 
                "name": "Complete job", 
                "number": 19, 
                "completed_at": "2021-01-30T12:08:16.000Z", 
                "started_at": "2021-01-30T12:08:16.000Z", 
                "conclusion": "success"
            }
        ], 
        "head_sha": "a9cce43411b50a8ad8b6705a6a5fb28b4ff88206", 
        "started_at": "2021-01-30T12:07:20Z", 
        "id": 1797249503, 
        "conclusion": "success"
    }, 
    {
        "status": "completed", 
        "check_run_url": "https://api.github.com/repos/soramitsu/soramitsu-hunter/check-runs/1797249486", 
        "name": "spdlog android-ndk-r17-api-24-arm64-v8a-clang-libcxx14 ubuntu-16.04", 
        "run_id": 523288990, 
        "url": "https://api.github.com/repos/soramitsu/soramitsu-hunter/actions/jobs/1797249486", 
        "html_url": "https://github.com/soramitsu/soramitsu-hunter/runs/1797249486", 
        "completed_at": "2021-01-30T12:09:41Z", 
        "run_url": "https://api.github.com/repos/soramitsu/soramitsu-hunter/actions/runs/523288990", 
        "node_id": "MDg6Q2hlY2tSdW4xNzk3MjQ5NDg2", 
        "steps": [
            {
                "status": "completed", 
                "name": "Set up job", 
                "number": 1, 
                "completed_at": "2021-01-30T12:07:23.000Z", 
                "started_at": "2021-01-30T12:07:21.000Z", 
                "conclusion": "success"
            }, 
            {
                "status": "completed", 
                "name": "Git checkout with submodules", 
                "number": 2, 
                "completed_at": "2021-01-30T12:07:27.000Z", 
                "started_at": "2021-01-30T12:07:23.000Z", 
                "conclusion": "success"
            }, 
            {
                "status": "completed", 
                "name": "Set up Python", 
                "number": 3, 
                "completed_at": "2021-01-30T12:07:27.000Z", 
                "started_at": "2021-01-30T12:07:27.000Z", 
                "conclusion": "success"
            }, 
            {
                "status": "completed", 
                "name": "Set up Python environment variable (Unix)", 
                "number": 4, 
                "completed_at": "2021-01-30T12:07:27.000Z", 
                "started_at": "2021-01-30T12:07:27.000Z", 
                "conclusion": "success"
            }, 
            {
                "status": "completed", 
                "name": "Set up Python environment variable (Windows)", 
                "number": 5, 
                "completed_at": "2021-01-30T12:07:27.000Z", 
                "started_at": "2021-01-30T12:07:27.000Z", 
                "conclusion": "skipped"
            }, 
            {
                "status": "completed", 
                "name": "Extract branch name", 
                "number": 6, 
                "completed_at": "2021-01-30T12:07:27.000Z", 
                "started_at": "2021-01-30T12:07:27.000Z", 
                "conclusion": "success"
            }, 
            {
                "status": "completed", 
                "name": "Upgrade pip", 
                "number": 7, 
                "completed_at": "2021-01-30T12:07:28.000Z", 
                "started_at": "2021-01-30T12:07:27.000Z", 
                "conclusion": "success"
            }, 
            {
                "status": "completed", 
                "name": "Build on Unix", 
                "number": 8, 
                "completed_at": "2021-01-30T12:09:41.000Z", 
                "started_at": "2021-01-30T12:07:28.000Z", 
                "conclusion": "success"
            }, 
            {
                "status": "completed", 
                "name": "Build on Windows", 
                "number": 9, 
                "completed_at": "2021-01-30T12:09:41.000Z", 
                "started_at": "2021-01-30T12:09:41.000Z", 
                "conclusion": "skipped"
            }, 
            {
                "status": "completed", 
                "name": "Post Git checkout with submodules", 
                "number": 18, 
                "completed_at": "2021-01-30T12:09:41.000Z", 
                "started_at": "2021-01-30T12:09:41.000Z", 
                "conclusion": "success"
            }, 
            {
                "status": "completed", 
                "name": "Complete job", 
                "number": 19, 
                "completed_at": "2021-01-30T12:09:41.000Z", 
                "started_at": "2021-01-30T12:09:41.000Z", 
                "conclusion": "success"
            }
        ], 
        "head_sha": "a9cce43411b50a8ad8b6705a6a5fb28b4ff88206", 
        "started_at": "2021-01-30T12:07:21Z", 
        "id": 1797249486, 
        "conclusion": "success"
    }, 
    {
        "status": "completed", 
        "check_run_url": "https://api.github.com/repos/soramitsu/soramitsu-hunter/check-runs/1797249433", 
        "name": "spdlog clang-cxx17 ubuntu-16.04", 
        "run_id": 523288990, 
        "url": "https://api.github.com/repos/soramitsu/soramitsu-hunter/actions/jobs/1797249433", 
        "html_url": "https://github.com/soramitsu/soramitsu-hunter/runs/1797249433", 
        "completed_at": "2021-01-30T12:08:07Z", 
        "run_url": "https://api.github.com/repos/soramitsu/soramitsu-hunter/actions/runs/523288990", 
        "node_id": "MDg6Q2hlY2tSdW4xNzk3MjQ5NDMz", 
        "steps": [
            {
                "status": "completed", 
                "name": "Set up job", 
                "number": 1, 
                "completed_at": "2021-01-30T12:07:22.000Z", 
                "started_at": "2021-01-30T12:07:20.000Z", 
                "conclusion": "success"
            }, 
            {
                "status": "completed", 
                "name": "Git checkout with submodules", 
                "number": 2, 
                "completed_at": "2021-01-30T12:07:26.000Z", 
                "started_at": "2021-01-30T12:07:22.000Z", 
                "conclusion": "success"
            }, 
            {
                "status": "completed", 
                "name": "Set up Python", 
                "number": 3, 
                "completed_at": "2021-01-30T12:07:26.000Z", 
                "started_at": "2021-01-30T12:07:26.000Z", 
                "conclusion": "success"
            }, 
            {
                "status": "completed", 
                "name": "Set up Python environment variable (Unix)", 
                "number": 4, 
                "completed_at": "2021-01-30T12:07:26.000Z", 
                "started_at": "2021-01-30T12:07:26.000Z", 
                "conclusion": "success"
            }, 
            {
                "status": "completed", 
                "name": "Set up Python environment variable (Windows)", 
                "number": 5, 
                "completed_at": "2021-01-30T12:07:26.000Z", 
                "started_at": "2021-01-30T12:07:26.000Z", 
                "conclusion": "skipped"
            }, 
            {
                "status": "completed", 
                "name": "Extract branch name", 
                "number": 6, 
                "completed_at": "2021-01-30T12:07:26.000Z", 
                "started_at": "2021-01-30T12:07:26.000Z", 
                "conclusion": "success"
            }, 
            {
                "status": "completed", 
                "name": "Upgrade pip", 
                "number": 7, 
                "completed_at": "2021-01-30T12:07:28.000Z", 
                "started_at": "2021-01-30T12:07:26.000Z", 
                "conclusion": "success"
            }, 
            {
                "status": "completed", 
                "name": "Build on Unix", 
                "number": 8, 
                "completed_at": "2021-01-30T12:08:07.000Z", 
                "started_at": "2021-01-30T12:07:28.000Z", 
                "conclusion": "success"
            }, 
            {
                "status": "completed", 
                "name": "Build on Windows", 
                "number": 9, 
                "completed_at": "2021-01-30T12:08:07.000Z", 
                "started_at": "2021-01-30T12:08:07.000Z", 
                "conclusion": "skipped"
            }, 
            {
                "status": "completed", 
                "name": "Post Git checkout with submodules", 
                "number": 18, 
                "completed_at": "2021-01-30T12:08:07.000Z", 
                "started_at": "2021-01-30T12:08:07.000Z", 
                "conclusion": "success"
            }, 
            {
                "status": "completed", 
                "name": "Complete job", 
                "number": 19, 
                "completed_at": "2021-01-30T12:08:07.000Z", 
                "started_at": "2021-01-30T12:08:07.000Z", 
                "conclusion": "success"
            }
        ], 
        "head_sha": "a9cce43411b50a8ad8b6705a6a5fb28b4ff88206", 
        "started_at": "2021-01-30T12:07:20Z", 
        "id": 1797249433, 
        "conclusion": "success"
    }, 
    {
        "status": "completed", 
        "check_run_url": "https://api.github.com/repos/soramitsu/soramitsu-hunter/check-runs/1797249446", 
        "name": "spdlog gcc-7-cxx17 ubuntu-16.04", 
        "run_id": 523288990, 
        "url": "https://api.github.com/repos/soramitsu/soramitsu-hunter/actions/jobs/1797249446", 
        "html_url": "https://github.com/soramitsu/soramitsu-hunter/runs/1797249446", 
        "completed_at": "2021-01-30T12:08:02Z", 
        "run_url": "https://api.github.com/repos/soramitsu/soramitsu-hunter/actions/runs/523288990", 
        "node_id": "MDg6Q2hlY2tSdW4xNzk3MjQ5NDQ2", 
        "steps": [
            {
                "status": "completed", 
                "name": "Set up job", 
                "number": 1, 
                "completed_at": "2021-01-30T12:07:22.000Z", 
                "started_at": "2021-01-30T12:07:20.000Z", 
                "conclusion": "success"
            }, 
            {
                "status": "completed", 
                "name": "Git checkout with submodules", 
                "number": 2, 
                "completed_at": "2021-01-30T12:07:26.000Z", 
                "started_at": "2021-01-30T12:07:22.000Z", 
                "conclusion": "success"
            }, 
            {
                "status": "completed", 
                "name": "Set up Python", 
                "number": 3, 
                "completed_at": "2021-01-30T12:07:26.000Z", 
                "started_at": "2021-01-30T12:07:26.000Z", 
                "conclusion": "success"
            }, 
            {
                "status": "completed", 
                "name": "Set up Python environment variable (Unix)", 
                "number": 4, 
                "completed_at": "2021-01-30T12:07:26.000Z", 
                "started_at": "2021-01-30T12:07:26.000Z", 
                "conclusion": "success"
            }, 
            {
                "status": "completed", 
                "name": "Set up Python environment variable (Windows)", 
                "number": 5, 
                "completed_at": "2021-01-30T12:07:26.000Z", 
                "started_at": "2021-01-30T12:07:26.000Z", 
                "conclusion": "skipped"
            }, 
            {
                "status": "completed", 
                "name": "Extract branch name", 
                "number": 6, 
                "completed_at": "2021-01-30T12:07:26.000Z", 
                "started_at": "2021-01-30T12:07:26.000Z", 
                "conclusion": "success"
            }, 
            {
                "status": "completed", 
                "name": "Upgrade pip", 
                "number": 7, 
                "completed_at": "2021-01-30T12:07:28.000Z", 
                "started_at": "2021-01-30T12:07:26.000Z", 
                "conclusion": "success"
            }, 
            {
                "status": "completed", 
                "name": "Build on Unix", 
                "number": 8, 
                "completed_at": "2021-01-30T12:08:02.000Z", 
                "started_at": "2021-01-30T12:07:28.000Z", 
                "conclusion": "success"
            }, 
            {
                "status": "completed", 
                "name": "Build on Windows", 
                "number": 9, 
                "completed_at": "2021-01-30T12:08:02.000Z", 
                "started_at": "2021-01-30T12:08:02.000Z", 
                "conclusion": "skipped"
            }, 
            {
                "status": "completed", 
                "name": "Post Git checkout with submodules", 
                "number": 18, 
                "completed_at": "2021-01-30T12:08:02.000Z", 
                "started_at": "2021-01-30T12:08:02.000Z", 
                "conclusion": "success"
            }, 
            {
                "status": "completed", 
                "name": "Complete job", 
                "number": 19, 
                "completed_at": "2021-01-30T12:08:02.000Z", 
                "started_at": "2021-01-30T12:08:02.000Z", 
                "conclusion": "success"
            }
        ], 
        "head_sha": "a9cce43411b50a8ad8b6705a6a5fb28b4ff88206", 
        "started_at": "2021-01-30T12:07:20Z", 
        "id": 1797249446, 
        "conclusion": "success"
    }, 
    {
        "status": "completed", 
        "check_run_url": "https://api.github.com/repos/soramitsu/soramitsu-hunter/check-runs/1797249457", 
        "name": "spdlog gcc-8-cxx17-fpic ubuntu-18.04", 
        "run_id": 523288990, 
        "url": "https://api.github.com/repos/soramitsu/soramitsu-hunter/actions/jobs/1797249457", 
        "html_url": "https://github.com/soramitsu/soramitsu-hunter/runs/1797249457", 
        "completed_at": "2021-01-30T12:08:13Z", 
        "run_url": "https://api.github.com/repos/soramitsu/soramitsu-hunter/actions/runs/523288990", 
        "node_id": "MDg6Q2hlY2tSdW4xNzk3MjQ5NDU3", 
        "steps": [
            {
                "status": "completed", 
                "name": "Set up job", 
                "number": 1, 
                "completed_at": "2021-01-30T12:07:22.000Z", 
                "started_at": "2021-01-30T12:07:20.000Z", 
                "conclusion": "success"
            }, 
            {
                "status": "completed", 
                "name": "Git checkout with submodules", 
                "number": 2, 
                "completed_at": "2021-01-30T12:07:26.000Z", 
                "started_at": "2021-01-30T12:07:22.000Z", 
                "conclusion": "success"
            }, 
            {
                "status": "completed", 
                "name": "Set up Python", 
                "number": 3, 
                "completed_at": "2021-01-30T12:07:26.000Z", 
                "started_at": "2021-01-30T12:07:26.000Z", 
                "conclusion": "success"
            }, 
            {
                "status": "completed", 
                "name": "Set up Python environment variable (Unix)", 
                "number": 4, 
                "completed_at": "2021-01-30T12:07:26.000Z", 
                "started_at": "2021-01-30T12:07:26.000Z", 
                "conclusion": "success"
            }, 
            {
                "status": "completed", 
                "name": "Set up Python environment variable (Windows)", 
                "number": 5, 
                "completed_at": "2021-01-30T12:07:26.000Z", 
                "started_at": "2021-01-30T12:07:26.000Z", 
                "conclusion": "skipped"
            }, 
            {
                "status": "completed", 
                "name": "Extract branch name", 
                "number": 6, 
                "completed_at": "2021-01-30T12:07:26.000Z", 
                "started_at": "2021-01-30T12:07:26.000Z", 
                "conclusion": "success"
            }, 
            {
                "status": "completed", 
                "name": "Upgrade pip", 
                "number": 7, 
                "completed_at": "2021-01-30T12:07:29.000Z", 
                "started_at": "2021-01-30T12:07:26.000Z", 
                "conclusion": "success"
            }, 
            {
                "status": "completed", 
                "name": "Build on Unix", 
                "number": 8, 
                "completed_at": "2021-01-30T12:08:12.000Z", 
                "started_at": "2021-01-30T12:07:29.000Z", 
                "conclusion": "success"
            }, 
            {
                "status": "completed", 
                "name": "Build on Windows", 
                "number": 9, 
                "completed_at": "2021-01-30T12:08:12.000Z", 
                "started_at": "2021-01-30T12:08:12.000Z", 
                "conclusion": "skipped"
            }, 
            {
                "status": "completed", 
                "name": "Post Git checkout with submodules", 
                "number": 18, 
                "completed_at": "2021-01-30T12:08:13.000Z", 
                "started_at": "2021-01-30T12:08:12.000Z", 
                "conclusion": "success"
            }, 
            {
                "status": "completed", 
                "name": "Complete job", 
                "number": 19, 
                "completed_at": "2021-01-30T12:08:13.000Z", 
                "started_at": "2021-01-30T12:08:13.000Z", 
                "conclusion": "success"
            }
        ], 
        "head_sha": "a9cce43411b50a8ad8b6705a6a5fb28b4ff88206", 
        "started_at": "2021-01-30T12:07:20Z", 
        "id": 1797249457, 
        "conclusion": "success"
    }, 
    {
        "status": "completed", 
        "check_run_url": "https://api.github.com/repos/soramitsu/soramitsu-hunter/check-runs/1797249471", 
        "name": "spdlog gcc-9-cxx17-fpic ubuntu-20.04", 
        "run_id": 523288990, 
        "url": "https://api.github.com/repos/soramitsu/soramitsu-hunter/actions/jobs/1797249471", 
        "html_url": "https://github.com/soramitsu/soramitsu-hunter/runs/1797249471", 
        "completed_at": "2021-01-30T12:08:27Z", 
        "run_url": "https://api.github.com/repos/soramitsu/soramitsu-hunter/actions/runs/523288990", 
        "node_id": "MDg6Q2hlY2tSdW4xNzk3MjQ5NDcx", 
        "steps": [
            {
                "status": "completed", 
                "name": "Set up job", 
                "number": 1, 
                "completed_at": "2021-01-30T12:07:34.000Z", 
                "started_at": "2021-01-30T12:07:31.000Z", 
                "conclusion": "success"
            }, 
            {
                "status": "completed", 
                "name": "Git checkout with submodules", 
                "number": 2, 
                "completed_at": "2021-01-30T12:07:37.000Z", 
                "started_at": "2021-01-30T12:07:34.000Z", 
                "conclusion": "success"
            }, 
            {
                "status": "completed", 
                "name": "Set up Python", 
                "number": 3, 
                "completed_at": "2021-01-30T12:07:37.000Z", 
                "started_at": "2021-01-30T12:07:37.000Z", 
                "conclusion": "success"
            }, 
            {
                "status": "completed", 
                "name": "Set up Python environment variable (Unix)", 
                "number": 4, 
                "completed_at": "2021-01-30T12:07:37.000Z", 
                "started_at": "2021-01-30T12:07:37.000Z", 
                "conclusion": "success"
            }, 
            {
                "status": "completed", 
                "name": "Set up Python environment variable (Windows)", 
                "number": 5, 
                "completed_at": "2021-01-30T12:07:37.000Z", 
                "started_at": "2021-01-30T12:07:37.000Z", 
                "conclusion": "skipped"
            }, 
            {
                "status": "completed", 
                "name": "Extract branch name", 
                "number": 6, 
                "completed_at": "2021-01-30T12:07:37.000Z", 
                "started_at": "2021-01-30T12:07:37.000Z", 
                "conclusion": "success"
            }, 
            {
                "status": "completed", 
                "name": "Upgrade pip", 
                "number": 7, 
                "completed_at": "2021-01-30T12:07:42.000Z", 
                "started_at": "2021-01-30T12:07:37.000Z", 
                "conclusion": "success"
            }, 
            {
                "status": "completed", 
                "name": "Build on Unix", 
                "number": 8, 
                "completed_at": "2021-01-30T12:08:27.000Z", 
                "started_at": "2021-01-30T12:07:42.000Z", 
                "conclusion": "success"
            }, 
            {
                "status": "completed", 
                "name": "Build on Windows", 
                "number": 9, 
                "completed_at": "2021-01-30T12:08:27.000Z", 
                "started_at": "2021-01-30T12:08:27.000Z", 
                "conclusion": "skipped"
            }, 
            {
                "status": "completed", 
                "name": "Post Git checkout with submodules", 
                "number": 18, 
                "completed_at": "2021-01-30T12:08:27.000Z", 
                "started_at": "2021-01-30T12:08:27.000Z", 
                "conclusion": "success"
            }, 
            {
                "status": "completed", 
                "name": "Complete job", 
                "number": 19, 
                "completed_at": "2021-01-30T12:08:27.000Z", 
                "started_at": "2021-01-30T12:08:27.000Z", 
                "conclusion": "success"
            }
        ], 
        "head_sha": "a9cce43411b50a8ad8b6705a6a5fb28b4ff88206", 
        "started_at": "2021-01-30T12:07:31Z", 
        "id": 1797249471, 
        "conclusion": "success"
    }, 
    {
        "status": "completed", 
        "check_run_url": "https://api.github.com/repos/soramitsu/soramitsu-hunter/check-runs/1797249560", 
        "name": "spdlog ios-nocodesign-13-2-dep-9-3 macos-10.15", 
        "run_id": 523288990, 
        "url": "https://api.github.com/repos/soramitsu/soramitsu-hunter/actions/jobs/1797249560", 
        "html_url": "https://github.com/soramitsu/soramitsu-hunter/runs/1797249560", 
        "completed_at": "2021-01-30T12:08:06Z", 
        "run_url": "https://api.github.com/repos/soramitsu/soramitsu-hunter/actions/runs/523288990", 
        "node_id": "MDg6Q2hlY2tSdW4xNzk3MjQ5NTYw", 
        "steps": [
            {
                "status": "completed", 
                "name": "Set up job", 
                "number": 1, 
                "completed_at": "2021-01-30T12:07:29.000Z", 
                "started_at": "2021-01-30T12:07:26.000Z", 
                "conclusion": "success"
            }, 
            {
                "status": "completed", 
                "name": "Git checkout with submodules", 
                "number": 2, 
                "completed_at": "2021-01-30T12:07:34.000Z", 
                "started_at": "2021-01-30T12:07:29.000Z", 
                "conclusion": "success"
            }, 
            {
                "status": "completed", 
                "name": "Set up Python", 
                "number": 3, 
                "completed_at": "2021-01-30T12:07:34.000Z", 
                "started_at": "2021-01-30T12:07:34.000Z", 
                "conclusion": "success"
            }, 
            {
                "status": "completed", 
                "name": "Set up Python environment variable (Unix)", 
                "number": 4, 
                "completed_at": "2021-01-30T12:07:34.000Z", 
                "started_at": "2021-01-30T12:07:34.000Z", 
                "conclusion": "success"
            }, 
            {
                "status": "completed", 
                "name": "Set up Python environment variable (Windows)", 
                "number": 5, 
                "completed_at": "2021-01-30T12:07:34.000Z", 
                "started_at": "2021-01-30T12:07:34.000Z", 
                "conclusion": "skipped"
            }, 
            {
                "status": "completed", 
                "name": "Extract branch name", 
                "number": 6, 
                "completed_at": "2021-01-30T12:07:34.000Z", 
                "started_at": "2021-01-30T12:07:34.000Z", 
                "conclusion": "success"
            }, 
            {
                "status": "completed", 
                "name": "Upgrade pip", 
                "number": 7, 
                "completed_at": "2021-01-30T12:07:36.000Z", 
                "started_at": "2021-01-30T12:07:34.000Z", 
                "conclusion": "success"
            }, 
            {
                "status": "completed", 
                "name": "Build on Unix", 
                "number": 8, 
                "completed_at": "2021-01-30T12:08:06.000Z", 
                "started_at": "2021-01-30T12:07:36.000Z", 
                "conclusion": "failure"
            }, 
            {
                "status": "completed", 
                "name": "Build on Windows", 
                "number": 9, 
                "completed_at": "2021-01-30T12:08:06.000Z", 
                "started_at": "2021-01-30T12:08:06.000Z", 
                "conclusion": "skipped"
            }, 
            {
                "status": "completed", 
                "name": "Post Git checkout with submodules", 
                "number": 18, 
                "completed_at": "2021-01-30T12:08:06.000Z", 
                "started_at": "2021-01-30T12:08:06.000Z", 
                "conclusion": "success"
            }, 
            {
                "status": "completed", 
                "name": "Complete job", 
                "number": 19, 
                "completed_at": "2021-01-30T12:08:06.000Z", 
                "started_at": "2021-01-30T12:08:06.000Z", 
                "conclusion": "success"
            }
        ], 
        "head_sha": "a9cce43411b50a8ad8b6705a6a5fb28b4ff88206", 
        "started_at": "2021-01-30T12:07:26Z", 
        "id": 1797249560, 
        "conclusion": "failure"
    }, 
    {
        "status": "completed", 
        "check_run_url": "https://api.github.com/repos/soramitsu/soramitsu-hunter/check-runs/1797249613", 
        "name": "spdlog mingw-cxx17 windows-2016", 
        "run_id": 523288990, 
        "url": "https://api.github.com/repos/soramitsu/soramitsu-hunter/actions/jobs/1797249613", 
        "html_url": "https://github.com/soramitsu/soramitsu-hunter/runs/1797249613", 
        "completed_at": "2021-01-30T12:09:27Z", 
        "run_url": "https://api.github.com/repos/soramitsu/soramitsu-hunter/actions/runs/523288990", 
        "node_id": "MDg6Q2hlY2tSdW4xNzk3MjQ5NjEz", 
        "steps": [
            {
                "status": "completed", 
                "name": "Set up job", 
                "number": 1, 
                "completed_at": "2021-01-30T12:07:22.000Z", 
                "started_at": "2021-01-30T12:07:20.000Z", 
                "conclusion": "success"
            }, 
            {
                "status": "completed", 
                "name": "Git checkout with submodules", 
                "number": 2, 
                "completed_at": "2021-01-30T12:07:36.000Z", 
                "started_at": "2021-01-30T12:07:22.000Z", 
                "conclusion": "success"
            }, 
            {
                "status": "completed", 
                "name": "Set up Python", 
                "number": 3, 
                "completed_at": "2021-01-30T12:07:37.000Z", 
                "started_at": "2021-01-30T12:07:36.000Z", 
                "conclusion": "success"
            }, 
            {
                "status": "completed", 
                "name": "Set up Python environment variable (Unix)", 
                "number": 4, 
                "completed_at": "2021-01-30T12:07:37.000Z", 
                "started_at": "2021-01-30T12:07:37.000Z", 
                "conclusion": "skipped"
            }, 
            {
                "status": "completed", 
                "name": "Set up Python environment variable (Windows)", 
                "number": 5, 
                "completed_at": "2021-01-30T12:07:38.000Z", 
                "started_at": "2021-01-30T12:07:37.000Z", 
                "conclusion": "success"
            }, 
            {
                "status": "completed", 
                "name": "Extract branch name", 
                "number": 6, 
                "completed_at": "2021-01-30T12:07:38.000Z", 
                "started_at": "2021-01-30T12:07:38.000Z", 
                "conclusion": "success"
            }, 
            {
                "status": "completed", 
                "name": "Upgrade pip", 
                "number": 7, 
                "completed_at": "2021-01-30T12:07:52.000Z", 
                "started_at": "2021-01-30T12:07:38.000Z", 
                "conclusion": "success"
            }, 
            {
                "status": "completed", 
                "name": "Build on Unix", 
                "number": 8, 
                "completed_at": "2021-01-30T12:07:52.000Z", 
                "started_at": "2021-01-30T12:07:52.000Z", 
                "conclusion": "skipped"
            }, 
            {
                "status": "completed", 
                "name": "Build on Windows", 
                "number": 9, 
                "completed_at": "2021-01-30T12:09:24.000Z", 
                "started_at": "2021-01-30T12:07:52.000Z", 
                "conclusion": "success"
            }, 
            {
                "status": "completed", 
                "name": "Post Git checkout with submodules", 
                "number": 18, 
                "completed_at": "2021-01-30T12:09:27.000Z", 
                "started_at": "2021-01-30T12:09:24.000Z", 
                "conclusion": "success"
            }, 
            {
                "status": "completed", 
                "name": "Complete job", 
                "number": 19, 
                "completed_at": "2021-01-30T12:09:27.000Z", 
                "started_at": "2021-01-30T12:09:27.000Z", 
                "conclusion": "success"
            }
        ], 
        "head_sha": "a9cce43411b50a8ad8b6705a6a5fb28b4ff88206", 
        "started_at": "2021-01-30T12:07:20Z", 
        "id": 1797249613, 
        "conclusion": "success"
    }, 
    {
        "status": "completed", 
        "check_run_url": "https://api.github.com/repos/soramitsu/soramitsu-hunter/check-runs/1797249616", 
        "name": "spdlog msys-cxx17 windows-2016", 
        "run_id": 523288990, 
        "url": "https://api.github.com/repos/soramitsu/soramitsu-hunter/actions/jobs/1797249616", 
        "html_url": "https://github.com/soramitsu/soramitsu-hunter/runs/1797249616", 
        "completed_at": "2021-01-30T12:11:02Z", 
        "run_url": "https://api.github.com/repos/soramitsu/soramitsu-hunter/actions/runs/523288990", 
        "node_id": "MDg6Q2hlY2tSdW4xNzk3MjQ5NjE2", 
        "steps": [
            {
                "status": "completed", 
                "name": "Set up job", 
                "number": 1, 
                "completed_at": "2021-01-30T12:07:23.000Z", 
                "started_at": "2021-01-30T12:07:21.000Z", 
                "conclusion": "success"
            }, 
            {
                "status": "completed", 
                "name": "Git checkout with submodules", 
                "number": 2, 
                "completed_at": "2021-01-30T12:07:39.000Z", 
                "started_at": "2021-01-30T12:07:23.000Z", 
                "conclusion": "success"
            }, 
            {
                "status": "completed", 
                "name": "Set up Python", 
                "number": 3, 
                "completed_at": "2021-01-30T12:07:40.000Z", 
                "started_at": "2021-01-30T12:07:39.000Z", 
                "conclusion": "success"
            }, 
            {
                "status": "completed", 
                "name": "Set up Python environment variable (Unix)", 
                "number": 4, 
                "completed_at": "2021-01-30T12:07:40.000Z", 
                "started_at": "2021-01-30T12:07:40.000Z", 
                "conclusion": "skipped"
            }, 
            {
                "status": "completed", 
                "name": "Set up Python environment variable (Windows)", 
                "number": 5, 
                "completed_at": "2021-01-30T12:07:41.000Z", 
                "started_at": "2021-01-30T12:07:40.000Z", 
                "conclusion": "success"
            }, 
            {
                "status": "completed", 
                "name": "Extract branch name", 
                "number": 6, 
                "completed_at": "2021-01-30T12:07:41.000Z", 
                "started_at": "2021-01-30T12:07:41.000Z", 
                "conclusion": "success"
            }, 
            {
                "status": "completed", 
                "name": "Upgrade pip", 
                "number": 7, 
                "completed_at": "2021-01-30T12:07:55.000Z", 
                "started_at": "2021-01-30T12:07:41.000Z", 
                "conclusion": "success"
            }, 
            {
                "status": "completed", 
                "name": "Build on Unix", 
                "number": 8, 
                "completed_at": "2021-01-30T12:07:55.000Z", 
                "started_at": "2021-01-30T12:07:55.000Z", 
                "conclusion": "skipped"
            }, 
            {
                "status": "completed", 
                "name": "Build on Windows", 
                "number": 9, 
                "completed_at": "2021-01-30T12:10:59.000Z", 
                "started_at": "2021-01-30T12:07:55.000Z", 
                "conclusion": "success"
            }, 
            {
                "status": "completed", 
                "name": "Post Git checkout with submodules", 
                "number": 18, 
                "completed_at": "2021-01-30T12:11:02.000Z", 
                "started_at": "2021-01-30T12:10:59.000Z", 
                "conclusion": "success"
            }, 
            {
                "status": "completed", 
                "name": "Complete job", 
                "number": 19, 
                "completed_at": "2021-01-30T12:11:02.000Z", 
                "started_at": "2021-01-30T12:11:02.000Z", 
                "conclusion": "success"
            }
        ], 
        "head_sha": "a9cce43411b50a8ad8b6705a6a5fb28b4ff88206", 
        "started_at": "2021-01-30T12:07:21Z", 
        "id": 1797249616, 
        "conclusion": "success"
    }, 
    {
        "status": "completed", 
        "check_run_url": "https://api.github.com/repos/soramitsu/soramitsu-hunter/check-runs/1797249568", 
        "name": "spdlog ninja-vs-15-2017-win64-cxx17 windows-2016", 
        "run_id": 523288990, 
        "url": "https://api.github.com/repos/soramitsu/soramitsu-hunter/actions/jobs/1797249568", 
        "html_url": "https://github.com/soramitsu/soramitsu-hunter/runs/1797249568", 
        "completed_at": "2021-01-30T12:09:16Z", 
        "run_url": "https://api.github.com/repos/soramitsu/soramitsu-hunter/actions/runs/523288990", 
        "node_id": "MDg6Q2hlY2tSdW4xNzk3MjQ5NTY4", 
        "steps": [
            {
                "status": "completed", 
                "name": "Set up job", 
                "number": 1, 
                "completed_at": "2021-01-30T12:07:23.000Z", 
                "started_at": "2021-01-30T12:07:21.000Z", 
                "conclusion": "success"
            }, 
            {
                "status": "completed", 
                "name": "Git checkout with submodules", 
                "number": 2, 
                "completed_at": "2021-01-30T12:07:39.000Z", 
                "started_at": "2021-01-30T12:07:23.000Z", 
                "conclusion": "success"
            }, 
            {
                "status": "completed", 
                "name": "Set up Python", 
                "number": 3, 
                "completed_at": "2021-01-30T12:07:40.000Z", 
                "started_at": "2021-01-30T12:07:39.000Z", 
                "conclusion": "success"
            }, 
            {
                "status": "completed", 
                "name": "Set up Python environment variable (Unix)", 
                "number": 4, 
                "completed_at": "2021-01-30T12:07:40.000Z", 
                "started_at": "2021-01-30T12:07:40.000Z", 
                "conclusion": "skipped"
            }, 
            {
                "status": "completed", 
                "name": "Set up Python environment variable (Windows)", 
                "number": 5, 
                "completed_at": "2021-01-30T12:07:41.000Z", 
                "started_at": "2021-01-30T12:07:40.000Z", 
                "conclusion": "success"
            }, 
            {
                "status": "completed", 
                "name": "Extract branch name", 
                "number": 6, 
                "completed_at": "2021-01-30T12:07:41.000Z", 
                "started_at": "2021-01-30T12:07:41.000Z", 
                "conclusion": "success"
            }, 
            {
                "status": "completed", 
                "name": "Upgrade pip", 
                "number": 7, 
                "completed_at": "2021-01-30T12:07:54.000Z", 
                "started_at": "2021-01-30T12:07:41.000Z", 
                "conclusion": "success"
            }, 
            {
                "status": "completed", 
                "name": "Build on Unix", 
                "number": 8, 
                "completed_at": "2021-01-30T12:07:54.000Z", 
                "started_at": "2021-01-30T12:07:54.000Z", 
                "conclusion": "skipped"
            }, 
            {
                "status": "completed", 
                "name": "Build on Windows", 
                "number": 9, 
                "completed_at": "2021-01-30T12:09:13.000Z", 
                "started_at": "2021-01-30T12:07:54.000Z", 
                "conclusion": "success"
            }, 
            {
                "status": "completed", 
                "name": "Post Git checkout with submodules", 
                "number": 18, 
                "completed_at": "2021-01-30T12:09:16.000Z", 
                "started_at": "2021-01-30T12:09:13.000Z", 
                "conclusion": "success"
            }, 
            {
                "status": "completed", 
                "name": "Complete job", 
                "number": 19, 
                "completed_at": "2021-01-30T12:09:16.000Z", 
                "started_at": "2021-01-30T12:09:16.000Z", 
                "conclusion": "success"
            }
        ], 
        "head_sha": "a9cce43411b50a8ad8b6705a6a5fb28b4ff88206", 
        "started_at": "2021-01-30T12:07:21Z", 
        "id": 1797249568, 
        "conclusion": "success"
    }, 
    {
        "status": "completed", 
        "check_run_url": "https://api.github.com/repos/soramitsu/soramitsu-hunter/check-runs/1797249575", 
        "name": "spdlog nmake-vs-15-2017-win64-cxx17 windows-2016", 
        "run_id": 523288990, 
        "url": "https://api.github.com/repos/soramitsu/soramitsu-hunter/actions/jobs/1797249575", 
        "html_url": "https://github.com/soramitsu/soramitsu-hunter/runs/1797249575", 
        "completed_at": "2021-01-30T12:09:26Z", 
        "run_url": "https://api.github.com/repos/soramitsu/soramitsu-hunter/actions/runs/523288990", 
        "node_id": "MDg6Q2hlY2tSdW4xNzk3MjQ5NTc1", 
        "steps": [
            {
                "status": "completed", 
                "name": "Set up job", 
                "number": 1, 
                "completed_at": "2021-01-30T12:07:22.000Z", 
                "started_at": "2021-01-30T12:07:21.000Z", 
                "conclusion": "success"
            }, 
            {
                "status": "completed", 
                "name": "Git checkout with submodules", 
                "number": 2, 
                "completed_at": "2021-01-30T12:07:38.000Z", 
                "started_at": "2021-01-30T12:07:22.000Z", 
                "conclusion": "success"
            }, 
            {
                "status": "completed", 
                "name": "Set up Python", 
                "number": 3, 
                "completed_at": "2021-01-30T12:07:38.000Z", 
                "started_at": "2021-01-30T12:07:38.000Z", 
                "conclusion": "success"
            }, 
            {
                "status": "completed", 
                "name": "Set up Python environment variable (Unix)", 
                "number": 4, 
                "completed_at": "2021-01-30T12:07:38.000Z", 
                "started_at": "2021-01-30T12:07:38.000Z", 
                "conclusion": "skipped"
            }, 
            {
                "status": "completed", 
                "name": "Set up Python environment variable (Windows)", 
                "number": 5, 
                "completed_at": "2021-01-30T12:07:39.000Z", 
                "started_at": "2021-01-30T12:07:38.000Z", 
                "conclusion": "success"
            }, 
            {
                "status": "completed", 
                "name": "Extract branch name", 
                "number": 6, 
                "completed_at": "2021-01-30T12:07:39.000Z", 
                "started_at": "2021-01-30T12:07:39.000Z", 
                "conclusion": "success"
            }, 
            {
                "status": "completed", 
                "name": "Upgrade pip", 
                "number": 7, 
                "completed_at": "2021-01-30T12:07:51.000Z", 
                "started_at": "2021-01-30T12:07:39.000Z", 
                "conclusion": "success"
            }, 
            {
                "status": "completed", 
                "name": "Build on Unix", 
                "number": 8, 
                "completed_at": "2021-01-30T12:07:51.000Z", 
                "started_at": "2021-01-30T12:07:51.000Z", 
                "conclusion": "skipped"
            }, 
            {
                "status": "completed", 
                "name": "Build on Windows", 
                "number": 9, 
                "completed_at": "2021-01-30T12:09:23.000Z", 
                "started_at": "2021-01-30T12:07:51.000Z", 
                "conclusion": "success"
            }, 
            {
                "status": "completed", 
                "name": "Post Git checkout with submodules", 
                "number": 18, 
                "completed_at": "2021-01-30T12:09:26.000Z", 
                "started_at": "2021-01-30T12:09:23.000Z", 
                "conclusion": "success"
            }, 
            {
                "status": "completed", 
                "name": "Complete job", 
                "number": 19, 
                "completed_at": "2021-01-30T12:09:26.000Z", 
                "started_at": "2021-01-30T12:09:26.000Z", 
                "conclusion": "success"
            }
        ], 
        "head_sha": "a9cce43411b50a8ad8b6705a6a5fb28b4ff88206", 
        "started_at": "2021-01-30T12:07:21Z", 
        "id": 1797249575, 
        "conclusion": "success"
    }, 
    {
        "status": "completed", 
        "check_run_url": "https://api.github.com/repos/soramitsu/soramitsu-hunter/check-runs/1797249550", 
        "name": "spdlog osx-10-13-cxx14 macos-10.15", 
        "run_id": 523288990, 
        "url": "https://api.github.com/repos/soramitsu/soramitsu-hunter/actions/jobs/1797249550", 
        "html_url": "https://github.com/soramitsu/soramitsu-hunter/runs/1797249550", 
        "completed_at": "2021-01-30T12:10:07Z", 
        "run_url": "https://api.github.com/repos/soramitsu/soramitsu-hunter/actions/runs/523288990", 
        "node_id": "MDg6Q2hlY2tSdW4xNzk3MjQ5NTUw", 
        "steps": [
            {
                "status": "completed", 
                "name": "Set up job", 
                "number": 1, 
                "completed_at": "2021-01-30T12:07:29.000Z", 
                "started_at": "2021-01-30T12:07:26.000Z", 
                "conclusion": "success"
            }, 
            {
                "status": "completed", 
                "name": "Git checkout with submodules", 
                "number": 2, 
                "completed_at": "2021-01-30T12:07:34.000Z", 
                "started_at": "2021-01-30T12:07:29.000Z", 
                "conclusion": "success"
            }, 
            {
                "status": "completed", 
                "name": "Set up Python", 
                "number": 3, 
                "completed_at": "2021-01-30T12:07:34.000Z", 
                "started_at": "2021-01-30T12:07:34.000Z", 
                "conclusion": "success"
            }, 
            {
                "status": "completed", 
                "name": "Set up Python environment variable (Unix)", 
                "number": 4, 
                "completed_at": "2021-01-30T12:07:34.000Z", 
                "started_at": "2021-01-30T12:07:34.000Z", 
                "conclusion": "success"
            }, 
            {
                "status": "completed", 
                "name": "Set up Python environment variable (Windows)", 
                "number": 5, 
                "completed_at": "2021-01-30T12:07:34.000Z", 
                "started_at": "2021-01-30T12:07:34.000Z", 
                "conclusion": "skipped"
            }, 
            {
                "status": "completed", 
                "name": "Extract branch name", 
                "number": 6, 
                "completed_at": "2021-01-30T12:07:34.000Z", 
                "started_at": "2021-01-30T12:07:34.000Z", 
                "conclusion": "success"
            }, 
            {
                "status": "completed", 
                "name": "Upgrade pip", 
                "number": 7, 
                "completed_at": "2021-01-30T12:07:35.000Z", 
                "started_at": "2021-01-30T12:07:34.000Z", 
                "conclusion": "success"
            }, 
            {
                "status": "completed", 
                "name": "Build on Unix", 
                "number": 8, 
                "completed_at": "2021-01-30T12:10:06.000Z", 
                "started_at": "2021-01-30T12:07:35.000Z", 
                "conclusion": "success"
            }, 
            {
                "status": "completed", 
                "name": "Build on Windows", 
                "number": 9, 
                "completed_at": "2021-01-30T12:10:06.000Z", 
                "started_at": "2021-01-30T12:10:06.000Z", 
                "conclusion": "skipped"
            }, 
            {
                "status": "completed", 
                "name": "Post Git checkout with submodules", 
                "number": 18, 
                "completed_at": "2021-01-30T12:10:07.000Z", 
                "started_at": "2021-01-30T12:10:06.000Z", 
                "conclusion": "success"
            }, 
            {
                "status": "completed", 
                "name": "Complete job", 
                "number": 19, 
                "completed_at": "2021-01-30T12:10:07.000Z", 
                "started_at": "2021-01-30T12:10:07.000Z", 
                "conclusion": "success"
            }
        ], 
        "head_sha": "a9cce43411b50a8ad8b6705a6a5fb28b4ff88206", 
        "started_at": "2021-01-30T12:07:26Z", 
        "id": 1797249550, 
        "conclusion": "success"
    }, 
    {
        "status": "completed", 
        "check_run_url": "https://api.github.com/repos/soramitsu/soramitsu-hunter/check-runs/1797249546", 
        "name": "spdlog osx-10-13-make-cxx14 macos-10.15", 
        "run_id": 523288990, 
        "url": "https://api.github.com/repos/soramitsu/soramitsu-hunter/actions/jobs/1797249546", 
        "html_url": "https://github.com/soramitsu/soramitsu-hunter/runs/1797249546", 
        "completed_at": "2021-01-30T12:08:26Z", 
        "run_url": "https://api.github.com/repos/soramitsu/soramitsu-hunter/actions/runs/523288990", 
        "node_id": "MDg6Q2hlY2tSdW4xNzk3MjQ5NTQ2", 
        "steps": [
            {
                "status": "completed", 
                "name": "Set up job", 
                "number": 1, 
                "completed_at": "2021-01-30T12:07:29.000Z", 
                "started_at": "2021-01-30T12:07:27.000Z", 
                "conclusion": "success"
            }, 
            {
                "status": "completed", 
                "name": "Git checkout with submodules", 
                "number": 2, 
                "completed_at": "2021-01-30T12:07:34.000Z", 
                "started_at": "2021-01-30T12:07:29.000Z", 
                "conclusion": "success"
            }, 
            {
                "status": "completed", 
                "name": "Set up Python", 
                "number": 3, 
                "completed_at": "2021-01-30T12:07:34.000Z", 
                "started_at": "2021-01-30T12:07:34.000Z", 
                "conclusion": "success"
            }, 
            {
                "status": "completed", 
                "name": "Set up Python environment variable (Unix)", 
                "number": 4, 
                "completed_at": "2021-01-30T12:07:34.000Z", 
                "started_at": "2021-01-30T12:07:34.000Z", 
                "conclusion": "success"
            }, 
            {
                "status": "completed", 
                "name": "Set up Python environment variable (Windows)", 
                "number": 5, 
                "completed_at": "2021-01-30T12:07:34.000Z", 
                "started_at": "2021-01-30T12:07:34.000Z", 
                "conclusion": "skipped"
            }, 
            {
                "status": "completed", 
                "name": "Extract branch name", 
                "number": 6, 
                "completed_at": "2021-01-30T12:07:34.000Z", 
                "started_at": "2021-01-30T12:07:34.000Z", 
                "conclusion": "success"
            }, 
            {
                "status": "completed", 
                "name": "Upgrade pip", 
                "number": 7, 
                "completed_at": "2021-01-30T12:07:36.000Z", 
                "started_at": "2021-01-30T12:07:34.000Z", 
                "conclusion": "success"
            }, 
            {
                "status": "completed", 
                "name": "Build on Unix", 
                "number": 8, 
                "completed_at": "2021-01-30T12:08:25.000Z", 
                "started_at": "2021-01-30T12:07:36.000Z", 
                "conclusion": "success"
            }, 
            {
                "status": "completed", 
                "name": "Build on Windows", 
                "number": 9, 
                "completed_at": "2021-01-30T12:08:25.000Z", 
                "started_at": "2021-01-30T12:08:25.000Z", 
                "conclusion": "skipped"
            }, 
            {
                "status": "completed", 
                "name": "Post Git checkout with submodules", 
                "number": 18, 
                "completed_at": "2021-01-30T12:08:26.000Z", 
                "started_at": "2021-01-30T12:08:25.000Z", 
                "conclusion": "success"
            }, 
            {
                "status": "completed", 
                "name": "Complete job", 
                "number": 19, 
                "completed_at": "2021-01-30T12:08:26.000Z", 
                "started_at": "2021-01-30T12:08:26.000Z", 
                "conclusion": "success"
            }
        ], 
        "head_sha": "a9cce43411b50a8ad8b6705a6a5fb28b4ff88206", 
        "started_at": "2021-01-30T12:07:27Z", 
        "id": 1797249546, 
        "conclusion": "success"
    }, 
    {
        "status": "completed", 
        "check_run_url": "https://api.github.com/repos/soramitsu/soramitsu-hunter/check-runs/1797249552", 
        "name": "spdlog osx-10-15-dep-10-10-cxx17 macos-10.15", 
        "run_id": 523288990, 
        "url": "https://api.github.com/repos/soramitsu/soramitsu-hunter/actions/jobs/1797249552", 
        "html_url": "https://github.com/soramitsu/soramitsu-hunter/runs/1797249552", 
        "completed_at": "2021-01-30T12:09:57Z", 
        "run_url": "https://api.github.com/repos/soramitsu/soramitsu-hunter/actions/runs/523288990", 
        "node_id": "MDg6Q2hlY2tSdW4xNzk3MjQ5NTUy", 
        "steps": [
            {
                "status": "completed", 
                "name": "Set up job", 
                "number": 1, 
                "completed_at": "2021-01-30T12:07:27.000Z", 
                "started_at": "2021-01-30T12:07:25.000Z", 
                "conclusion": "success"
            }, 
            {
                "status": "completed", 
                "name": "Git checkout with submodules", 
                "number": 2, 
                "completed_at": "2021-01-30T12:07:33.000Z", 
                "started_at": "2021-01-30T12:07:28.000Z", 
                "conclusion": "success"
            }, 
            {
                "status": "completed", 
                "name": "Set up Python", 
                "number": 3, 
                "completed_at": "2021-01-30T12:07:33.000Z", 
                "started_at": "2021-01-30T12:07:33.000Z", 
                "conclusion": "success"
            }, 
            {
                "status": "completed", 
                "name": "Set up Python environment variable (Unix)", 
                "number": 4, 
                "completed_at": "2021-01-30T12:07:33.000Z", 
                "started_at": "2021-01-30T12:07:33.000Z", 
                "conclusion": "success"
            }, 
            {
                "status": "completed", 
                "name": "Set up Python environment variable (Windows)", 
                "number": 5, 
                "completed_at": "2021-01-30T12:07:33.000Z", 
                "started_at": "2021-01-30T12:07:33.000Z", 
                "conclusion": "skipped"
            }, 
            {
                "status": "completed", 
                "name": "Extract branch name", 
                "number": 6, 
                "completed_at": "2021-01-30T12:07:33.000Z", 
                "started_at": "2021-01-30T12:07:33.000Z", 
                "conclusion": "success"
            }, 
            {
                "status": "completed", 
                "name": "Upgrade pip", 
                "number": 7, 
                "completed_at": "2021-01-30T12:07:35.000Z", 
                "started_at": "2021-01-30T12:07:33.000Z", 
                "conclusion": "success"
            }, 
            {
                "status": "completed", 
                "name": "Build on Unix", 
                "number": 8, 
                "completed_at": "2021-01-30T12:09:57.000Z", 
                "started_at": "2021-01-30T12:07:35.000Z", 
                "conclusion": "success"
            }, 
            {
                "status": "completed", 
                "name": "Build on Windows", 
                "number": 9, 
                "completed_at": "2021-01-30T12:09:57.000Z", 
                "started_at": "2021-01-30T12:09:57.000Z", 
                "conclusion": "skipped"
            }, 
            {
                "status": "completed", 
                "name": "Post Git checkout with submodules", 
                "number": 18, 
                "completed_at": "2021-01-30T12:09:57.000Z", 
                "started_at": "2021-01-30T12:09:57.000Z", 
                "conclusion": "success"
            }, 
            {
                "status": "completed", 
                "name": "Complete job", 
                "number": 19, 
                "completed_at": "2021-01-30T12:09:57.000Z", 
                "started_at": "2021-01-30T12:09:57.000Z", 
                "conclusion": "success"
            }
        ], 
        "head_sha": "a9cce43411b50a8ad8b6705a6a5fb28b4ff88206", 
        "started_at": "2021-01-30T12:07:25Z", 
        "id": 1797249552, 
        "conclusion": "success"
    }, 
    {
        "status": "completed", 
        "check_run_url": "https://api.github.com/repos/soramitsu/soramitsu-hunter/check-runs/1797249516", 
        "name": "spdlog sanitize-address-cxx17 ubuntu-16.04", 
        "run_id": 523288990, 
        "url": "https://api.github.com/repos/soramitsu/soramitsu-hunter/actions/jobs/1797249516", 
        "html_url": "https://github.com/soramitsu/soramitsu-hunter/runs/1797249516", 
        "completed_at": "2021-01-30T12:08:15Z", 
        "run_url": "https://api.github.com/repos/soramitsu/soramitsu-hunter/actions/runs/523288990", 
        "node_id": "MDg6Q2hlY2tSdW4xNzk3MjQ5NTE2", 
        "steps": [
            {
                "status": "completed", 
                "name": "Set up job", 
                "number": 1, 
                "completed_at": "2021-01-30T12:07:24.000Z", 
                "started_at": "2021-01-30T12:07:22.000Z", 
                "conclusion": "success"
            }, 
            {
                "status": "completed", 
                "name": "Git checkout with submodules", 
                "number": 2, 
                "completed_at": "2021-01-30T12:07:28.000Z", 
                "started_at": "2021-01-30T12:07:24.000Z", 
                "conclusion": "success"
            }, 
            {
                "status": "completed", 
                "name": "Set up Python", 
                "number": 3, 
                "completed_at": "2021-01-30T12:07:28.000Z", 
                "started_at": "2021-01-30T12:07:28.000Z", 
                "conclusion": "success"
            }, 
            {
                "status": "completed", 
                "name": "Set up Python environment variable (Unix)", 
                "number": 4, 
                "completed_at": "2021-01-30T12:07:28.000Z", 
                "started_at": "2021-01-30T12:07:28.000Z", 
                "conclusion": "success"
            }, 
            {
                "status": "completed", 
                "name": "Set up Python environment variable (Windows)", 
                "number": 5, 
                "completed_at": "2021-01-30T12:07:28.000Z", 
                "started_at": "2021-01-30T12:07:28.000Z", 
                "conclusion": "skipped"
            }, 
            {
                "status": "completed", 
                "name": "Extract branch name", 
                "number": 6, 
                "completed_at": "2021-01-30T12:07:28.000Z", 
                "started_at": "2021-01-30T12:07:28.000Z", 
                "conclusion": "success"
            }, 
            {
                "status": "completed", 
                "name": "Upgrade pip", 
                "number": 7, 
                "completed_at": "2021-01-30T12:07:30.000Z", 
                "started_at": "2021-01-30T12:07:28.000Z", 
                "conclusion": "success"
            }, 
            {
                "status": "completed", 
                "name": "Build on Unix", 
                "number": 8, 
                "completed_at": "2021-01-30T12:08:15.000Z", 
                "started_at": "2021-01-30T12:07:30.000Z", 
                "conclusion": "success"
            }, 
            {
                "status": "completed", 
                "name": "Build on Windows", 
                "number": 9, 
                "completed_at": "2021-01-30T12:08:15.000Z", 
                "started_at": "2021-01-30T12:08:15.000Z", 
                "conclusion": "skipped"
            }, 
            {
                "status": "completed", 
                "name": "Post Git checkout with submodules", 
                "number": 18, 
                "completed_at": "2021-01-30T12:08:15.000Z", 
                "started_at": "2021-01-30T12:08:15.000Z", 
                "conclusion": "success"
            }, 
            {
                "status": "completed", 
                "name": "Complete job", 
                "number": 19, 
                "completed_at": "2021-01-30T12:08:15.000Z", 
                "started_at": "2021-01-30T12:08:15.000Z", 
                "conclusion": "success"
            }
        ], 
        "head_sha": "a9cce43411b50a8ad8b6705a6a5fb28b4ff88206", 
        "started_at": "2021-01-30T12:07:22Z", 
        "id": 1797249516, 
        "conclusion": "success"
    }, 
    {
        "status": "completed", 
        "check_run_url": "https://api.github.com/repos/soramitsu/soramitsu-hunter/check-runs/1797249525", 
        "name": "spdlog sanitize-leak-cxx17 ubuntu-16.04", 
        "run_id": 523288990, 
        "url": "https://api.github.com/repos/soramitsu/soramitsu-hunter/actions/jobs/1797249525", 
        "html_url": "https://github.com/soramitsu/soramitsu-hunter/runs/1797249525", 
        "completed_at": "2021-01-30T12:08:07Z", 
        "run_url": "https://api.github.com/repos/soramitsu/soramitsu-hunter/actions/runs/523288990", 
        "node_id": "MDg6Q2hlY2tSdW4xNzk3MjQ5NTI1", 
        "steps": [
            {
                "status": "completed", 
                "name": "Set up job", 
                "number": 1, 
                "completed_at": "2021-01-30T12:07:23.000Z", 
                "started_at": "2021-01-30T12:07:21.000Z", 
                "conclusion": "success"
            }, 
            {
                "status": "completed", 
                "name": "Git checkout with submodules", 
                "number": 2, 
                "completed_at": "2021-01-30T12:07:27.000Z", 
                "started_at": "2021-01-30T12:07:23.000Z", 
                "conclusion": "success"
            }, 
            {
                "status": "completed", 
                "name": "Set up Python", 
                "number": 3, 
                "completed_at": "2021-01-30T12:07:27.000Z", 
                "started_at": "2021-01-30T12:07:27.000Z", 
                "conclusion": "success"
            }, 
            {
                "status": "completed", 
                "name": "Set up Python environment variable (Unix)", 
                "number": 4, 
                "completed_at": "2021-01-30T12:07:27.000Z", 
                "started_at": "2021-01-30T12:07:27.000Z", 
                "conclusion": "success"
            }, 
            {
                "status": "completed", 
                "name": "Set up Python environment variable (Windows)", 
                "number": 5, 
                "completed_at": "2021-01-30T12:07:27.000Z", 
                "started_at": "2021-01-30T12:07:27.000Z", 
                "conclusion": "skipped"
            }, 
            {
                "status": "completed", 
                "name": "Extract branch name", 
                "number": 6, 
                "completed_at": "2021-01-30T12:07:27.000Z", 
                "started_at": "2021-01-30T12:07:27.000Z", 
                "conclusion": "success"
            }, 
            {
                "status": "completed", 
                "name": "Upgrade pip", 
                "number": 7, 
                "completed_at": "2021-01-30T12:07:30.000Z", 
                "started_at": "2021-01-30T12:07:27.000Z", 
                "conclusion": "success"
            }, 
            {
                "status": "completed", 
                "name": "Build on Unix", 
                "number": 8, 
                "completed_at": "2021-01-30T12:08:07.000Z", 
                "started_at": "2021-01-30T12:07:30.000Z", 
                "conclusion": "success"
            }, 
            {
                "status": "completed", 
                "name": "Build on Windows", 
                "number": 9, 
                "completed_at": "2021-01-30T12:08:07.000Z", 
                "started_at": "2021-01-30T12:08:07.000Z", 
                "conclusion": "skipped"
            }, 
            {
                "status": "completed", 
                "name": "Post Git checkout with submodules", 
                "number": 18, 
                "completed_at": "2021-01-30T12:08:07.000Z", 
                "started_at": "2021-01-30T12:08:07.000Z", 
                "conclusion": "success"
            }, 
            {
                "status": "completed", 
                "name": "Complete job", 
                "number": 19, 
                "completed_at": "2021-01-30T12:08:07.000Z", 
                "started_at": "2021-01-30T12:08:07.000Z", 
                "conclusion": "success"
            }
        ], 
        "head_sha": "a9cce43411b50a8ad8b6705a6a5fb28b4ff88206", 
        "started_at": "2021-01-30T12:07:21Z", 
        "id": 1797249525, 
        "conclusion": "success"
    }, 
    {
        "status": "completed", 
        "check_run_url": "https://api.github.com/repos/soramitsu/soramitsu-hunter/check-runs/1797249535", 
        "name": "spdlog sanitize-thread-cxx17 ubuntu-16.04", 
        "run_id": 523288990, 
        "url": "https://api.github.com/repos/soramitsu/soramitsu-hunter/actions/jobs/1797249535", 
        "html_url": "https://github.com/soramitsu/soramitsu-hunter/runs/1797249535", 
        "completed_at": "2021-01-30T12:08:27Z", 
        "run_url": "https://api.github.com/repos/soramitsu/soramitsu-hunter/actions/runs/523288990", 
        "node_id": "MDg6Q2hlY2tSdW4xNzk3MjQ5NTM1", 
        "steps": [
            {
                "status": "completed", 
                "name": "Set up job", 
                "number": 1, 
                "completed_at": "2021-01-30T12:07:25.000Z", 
                "started_at": "2021-01-30T12:07:22.000Z", 
                "conclusion": "success"
            }, 
            {
                "status": "completed", 
                "name": "Git checkout with submodules", 
                "number": 2, 
                "completed_at": "2021-01-30T12:07:29.000Z", 
                "started_at": "2021-01-30T12:07:25.000Z", 
                "conclusion": "success"
            }, 
            {
                "status": "completed", 
                "name": "Set up Python", 
                "number": 3, 
                "completed_at": "2021-01-30T12:07:29.000Z", 
                "started_at": "2021-01-30T12:07:29.000Z", 
                "conclusion": "success"
            }, 
            {
                "status": "completed", 
                "name": "Set up Python environment variable (Unix)", 
                "number": 4, 
                "completed_at": "2021-01-30T12:07:29.000Z", 
                "started_at": "2021-01-30T12:07:29.000Z", 
                "conclusion": "success"
            }, 
            {
                "status": "completed", 
                "name": "Set up Python environment variable (Windows)", 
                "number": 5, 
                "completed_at": "2021-01-30T12:07:29.000Z", 
                "started_at": "2021-01-30T12:07:29.000Z", 
                "conclusion": "skipped"
            }, 
            {
                "status": "completed", 
                "name": "Extract branch name", 
                "number": 6, 
                "completed_at": "2021-01-30T12:07:29.000Z", 
                "started_at": "2021-01-30T12:07:29.000Z", 
                "conclusion": "success"
            }, 
            {
                "status": "completed", 
                "name": "Upgrade pip", 
                "number": 7, 
                "completed_at": "2021-01-30T12:07:32.000Z", 
                "started_at": "2021-01-30T12:07:29.000Z", 
                "conclusion": "success"
            }, 
            {
                "status": "completed", 
                "name": "Build on Unix", 
                "number": 8, 
                "completed_at": "2021-01-30T12:08:27.000Z", 
                "started_at": "2021-01-30T12:07:32.000Z", 
                "conclusion": "success"
            }, 
            {
                "status": "completed", 
                "name": "Build on Windows", 
                "number": 9, 
                "completed_at": "2021-01-30T12:08:27.000Z", 
                "started_at": "2021-01-30T12:08:27.000Z", 
                "conclusion": "skipped"
            }, 
            {
                "status": "completed", 
                "name": "Post Git checkout with submodules", 
                "number": 18, 
                "completed_at": "2021-01-30T12:08:27.000Z", 
                "started_at": "2021-01-30T12:08:27.000Z", 
                "conclusion": "success"
            }, 
            {
                "status": "completed", 
                "name": "Complete job", 
                "number": 19, 
                "completed_at": "2021-01-30T12:08:27.000Z", 
                "started_at": "2021-01-30T12:08:27.000Z", 
                "conclusion": "success"
            }
        ], 
        "head_sha": "a9cce43411b50a8ad8b6705a6a5fb28b4ff88206", 
        "started_at": "2021-01-30T12:07:22Z", 
        "id": 1797249535, 
        "conclusion": "success"
    }, 
    {
        "status": "completed", 
        "check_run_url": "https://api.github.com/repos/soramitsu/soramitsu-hunter/check-runs/1797249608", 
        "name": "spdlog vs-14-2015-sdk-8-1 windows-2016", 
        "run_id": 523288990, 
        "url": "https://api.github.com/repos/soramitsu/soramitsu-hunter/actions/jobs/1797249608", 
        "html_url": "https://github.com/soramitsu/soramitsu-hunter/runs/1797249608", 
        "completed_at": "2021-01-30T12:09:47Z", 
        "run_url": "https://api.github.com/repos/soramitsu/soramitsu-hunter/actions/runs/523288990", 
        "node_id": "MDg6Q2hlY2tSdW4xNzk3MjQ5NjA4", 
        "steps": [
            {
                "status": "completed", 
                "name": "Set up job", 
                "number": 1, 
                "completed_at": "2021-01-30T12:07:24.000Z", 
                "started_at": "2021-01-30T12:07:22.000Z", 
                "conclusion": "success"
            }, 
            {
                "status": "completed", 
                "name": "Git checkout with submodules", 
                "number": 2, 
                "completed_at": "2021-01-30T12:07:41.000Z", 
                "started_at": "2021-01-30T12:07:24.000Z", 
                "conclusion": "success"
            }, 
            {
                "status": "completed", 
                "name": "Set up Python", 
                "number": 3, 
                "completed_at": "2021-01-30T12:07:41.000Z", 
                "started_at": "2021-01-30T12:07:41.000Z", 
                "conclusion": "success"
            }, 
            {
                "status": "completed", 
                "name": "Set up Python environment variable (Unix)", 
                "number": 4, 
                "completed_at": "2021-01-30T12:07:41.000Z", 
                "started_at": "2021-01-30T12:07:41.000Z", 
                "conclusion": "skipped"
            }, 
            {
                "status": "completed", 
                "name": "Set up Python environment variable (Windows)", 
                "number": 5, 
                "completed_at": "2021-01-30T12:07:42.000Z", 
                "started_at": "2021-01-30T12:07:41.000Z", 
                "conclusion": "success"
            }, 
            {
                "status": "completed", 
                "name": "Extract branch name", 
                "number": 6, 
                "completed_at": "2021-01-30T12:07:42.000Z", 
                "started_at": "2021-01-30T12:07:42.000Z", 
                "conclusion": "success"
            }, 
            {
                "status": "completed", 
                "name": "Upgrade pip", 
                "number": 7, 
                "completed_at": "2021-01-30T12:07:55.000Z", 
                "started_at": "2021-01-30T12:07:42.000Z", 
                "conclusion": "success"
            }, 
            {
                "status": "completed", 
                "name": "Build on Unix", 
                "number": 8, 
                "completed_at": "2021-01-30T12:07:55.000Z", 
                "started_at": "2021-01-30T12:07:55.000Z", 
                "conclusion": "skipped"
            }, 
            {
                "status": "completed", 
                "name": "Build on Windows", 
                "number": 9, 
                "completed_at": "2021-01-30T12:09:43.000Z", 
                "started_at": "2021-01-30T12:07:55.000Z", 
                "conclusion": "success"
            }, 
            {
                "status": "completed", 
                "name": "Post Git checkout with submodules", 
                "number": 18, 
                "completed_at": "2021-01-30T12:09:46.000Z", 
                "started_at": "2021-01-30T12:09:43.000Z", 
                "conclusion": "success"
            }, 
            {
                "status": "completed", 
                "name": "Complete job", 
                "number": 19, 
                "completed_at": "2021-01-30T12:09:47.000Z", 
                "started_at": "2021-01-30T12:09:46.000Z", 
                "conclusion": "success"
            }
        ], 
        "head_sha": "a9cce43411b50a8ad8b6705a6a5fb28b4ff88206", 
        "started_at": "2021-01-30T12:07:22Z", 
        "id": 1797249608, 
        "conclusion": "success"
    }, 
    {
        "status": "completed", 
        "check_run_url": "https://api.github.com/repos/soramitsu/soramitsu-hunter/check-runs/1797249598", 
        "name": "spdlog vs-15-2017-win64-cxx17 windows-2016", 
        "run_id": 523288990, 
        "url": "https://api.github.com/repos/soramitsu/soramitsu-hunter/actions/jobs/1797249598", 
        "html_url": "https://github.com/soramitsu/soramitsu-hunter/runs/1797249598", 
        "completed_at": "2021-01-30T12:10:01Z", 
        "run_url": "https://api.github.com/repos/soramitsu/soramitsu-hunter/actions/runs/523288990", 
        "node_id": "MDg6Q2hlY2tSdW4xNzk3MjQ5NTk4", 
        "steps": [
            {
                "status": "completed", 
                "name": "Set up job", 
                "number": 1, 
                "completed_at": "2021-01-30T12:07:26.000Z", 
                "started_at": "2021-01-30T12:07:22.000Z", 
                "conclusion": "success"
            }, 
            {
                "status": "completed", 
                "name": "Git checkout with submodules", 
                "number": 2, 
                "completed_at": "2021-01-30T12:07:43.000Z", 
                "started_at": "2021-01-30T12:07:26.000Z", 
                "conclusion": "success"
            }, 
            {
                "status": "completed", 
                "name": "Set up Python", 
                "number": 3, 
                "completed_at": "2021-01-30T12:07:43.000Z", 
                "started_at": "2021-01-30T12:07:43.000Z", 
                "conclusion": "success"
            }, 
            {
                "status": "completed", 
                "name": "Set up Python environment variable (Unix)", 
                "number": 4, 
                "completed_at": "2021-01-30T12:07:43.000Z", 
                "started_at": "2021-01-30T12:07:43.000Z", 
                "conclusion": "skipped"
            }, 
            {
                "status": "completed", 
                "name": "Set up Python environment variable (Windows)", 
                "number": 5, 
                "completed_at": "2021-01-30T12:07:44.000Z", 
                "started_at": "2021-01-30T12:07:43.000Z", 
                "conclusion": "success"
            }, 
            {
                "status": "completed", 
                "name": "Extract branch name", 
                "number": 6, 
                "completed_at": "2021-01-30T12:07:44.000Z", 
                "started_at": "2021-01-30T12:07:44.000Z", 
                "conclusion": "success"
            }, 
            {
                "status": "completed", 
                "name": "Upgrade pip", 
                "number": 7, 
                "completed_at": "2021-01-30T12:07:57.000Z", 
                "started_at": "2021-01-30T12:07:44.000Z", 
                "conclusion": "success"
            }, 
            {
                "status": "completed", 
                "name": "Build on Unix", 
                "number": 8, 
                "completed_at": "2021-01-30T12:07:57.000Z", 
                "started_at": "2021-01-30T12:07:57.000Z", 
                "conclusion": "skipped"
            }, 
            {
                "status": "completed", 
                "name": "Build on Windows", 
                "number": 9, 
                "completed_at": "2021-01-30T12:09:57.000Z", 
                "started_at": "2021-01-30T12:07:57.000Z", 
                "conclusion": "success"
            }, 
            {
                "status": "completed", 
                "name": "Post Git checkout with submodules", 
                "number": 18, 
                "completed_at": "2021-01-30T12:10:01.000Z", 
                "started_at": "2021-01-30T12:09:57.000Z", 
                "conclusion": "success"
            }, 
            {
                "status": "completed", 
                "name": "Complete job", 
                "number": 19, 
                "completed_at": "2021-01-30T12:10:01.000Z", 
                "started_at": "2021-01-30T12:10:01.000Z", 
                "conclusion": "success"
            }
        ], 
        "head_sha": "a9cce43411b50a8ad8b6705a6a5fb28b4ff88206", 
        "started_at": "2021-01-30T12:07:22Z", 
        "id": 1797249598, 
        "conclusion": "success"
    }, 
    {
        "status": "completed", 
        "check_run_url": "https://api.github.com/repos/soramitsu/soramitsu-hunter/check-runs/1797249584", 
        "name": "spdlog vs-16-2019-win64-cxx17 windows-2019", 
        "run_id": 523288990, 
        "url": "https://api.github.com/repos/soramitsu/soramitsu-hunter/actions/jobs/1797249584", 
        "html_url": "https://github.com/soramitsu/soramitsu-hunter/runs/1797249584", 
        "completed_at": "2021-01-30T12:09:44Z", 
        "run_url": "https://api.github.com/repos/soramitsu/soramitsu-hunter/actions/runs/523288990", 
        "node_id": "MDg6Q2hlY2tSdW4xNzk3MjQ5NTg0", 
        "steps": [
            {
                "status": "completed", 
                "name": "Set up job", 
                "number": 1, 
                "completed_at": "2021-01-30T12:07:23.000Z", 
                "started_at": "2021-01-30T12:07:22.000Z", 
                "conclusion": "success"
            }, 
            {
                "status": "completed", 
                "name": "Git checkout with submodules", 
                "number": 2, 
                "completed_at": "2021-01-30T12:07:37.000Z", 
                "started_at": "2021-01-30T12:07:23.000Z", 
                "conclusion": "success"
            }, 
            {
                "status": "completed", 
                "name": "Set up Python", 
                "number": 3, 
                "completed_at": "2021-01-30T12:07:37.000Z", 
                "started_at": "2021-01-30T12:07:37.000Z", 
                "conclusion": "success"
            }, 
            {
                "status": "completed", 
                "name": "Set up Python environment variable (Unix)", 
                "number": 4, 
                "completed_at": "2021-01-30T12:07:37.000Z", 
                "started_at": "2021-01-30T12:07:37.000Z", 
                "conclusion": "skipped"
            }, 
            {
                "status": "completed", 
                "name": "Set up Python environment variable (Windows)", 
                "number": 5, 
                "completed_at": "2021-01-30T12:07:38.000Z", 
                "started_at": "2021-01-30T12:07:37.000Z", 
                "conclusion": "success"
            }, 
            {
                "status": "completed", 
                "name": "Extract branch name", 
                "number": 6, 
                "completed_at": "2021-01-30T12:07:39.000Z", 
                "started_at": "2021-01-30T12:07:38.000Z", 
                "conclusion": "success"
            }, 
            {
                "status": "completed", 
                "name": "Upgrade pip", 
                "number": 7, 
                "completed_at": "2021-01-30T12:07:50.000Z", 
                "started_at": "2021-01-30T12:07:39.000Z", 
                "conclusion": "success"
            }, 
            {
                "status": "completed", 
                "name": "Build on Unix", 
                "number": 8, 
                "completed_at": "2021-01-30T12:07:50.000Z", 
                "started_at": "2021-01-30T12:07:50.000Z", 
                "conclusion": "skipped"
            }, 
            {
                "status": "completed", 
                "name": "Build on Windows", 
                "number": 9, 
                "completed_at": "2021-01-30T12:09:41.000Z", 
                "started_at": "2021-01-30T12:07:50.000Z", 
                "conclusion": "success"
            }, 
            {
                "status": "completed", 
                "name": "Post Git checkout with submodules", 
                "number": 18, 
                "completed_at": "2021-01-30T12:09:44.000Z", 
                "started_at": "2021-01-30T12:09:41.000Z", 
                "conclusion": "success"
            }, 
            {
                "status": "completed", 
                "name": "Complete job", 
                "number": 19, 
                "completed_at": "2021-01-30T12:09:44.000Z", 
                "started_at": "2021-01-30T12:09:44.000Z", 
                "conclusion": "success"
            }
        ], 
        "head_sha": "a9cce43411b50a8ad8b6705a6a5fb28b4ff88206", 
        "started_at": "2021-01-30T12:07:22Z", 
        "id": 1797249584, 
        "conclusion": "success"
    }
]